README.md
autococonut/__init__.py
autococonut/autococonut.py
autococonut/autococonut_gui.py
autococonut/docs/autococonut.adoc
autococonut/docs/autococonut.html
autococonut/docs/autococonut.pdf
autococonut/docs/images/autococonut_add_event.png
autococonut/docs/images/autococonut_edit_event.png
autococonut/docs/images/autococonut_recording_started.png
autococonut/docs/images/autococonut_status.png
autococonut/engine/__init__.py
autococonut/engine/event_handler.py
autococonut/engine/interpreter.py
autococonut/engine/messages.py
autococonut/engine/screenshot_grabber.py
autococonut/engine/translator.py
autococonut/templates/page.adoc
autococonut/templates/page.html
autococonut/templates/page.pm
autococonut-0.9.16.dist-info/entry_points.txt
autococonut-0.9.16.dist-info/LICENSE
autococonut-0.9.16.dist-info/WHEEL
autococonut-0.9.16.dist-info/METADATA
autococonut-0.9.16.dist-info/RECORD
