Metadata-Version: 2.1
Name: autococonut
Version: 0.9.16
Summary: A workflow recording tool.
License: GPL-3.0-or-later
Author: Lukáš Růžička
Author-email: lruzicka@redhat.com
Requires-Python: >=3.9,<4.0
Classifier: License :: OSI Approved :: GNU General Public License v3 or later (GPLv3+)
Classifier: Programming Language :: Python :: 3
Classifier: Programming Language :: Python :: 3.9
Requires-Dist: Jinja2 (>=3.0.1,<4.0.0)
Requires-Dist: Pillow (>=8.2.0,<9.0.0)
Requires-Dist: evdev (>=1.4.0,<2.0.0)
Requires-Dist: pynput (>=1.7.3,<2.0.0)
Requires-Dist: pyscreenshot (>=3.0,<4.0)
